gimkit/__init__.py
gimkit/contexts.py
gimkit/dsls.py
gimkit/exceptions.py
gimkit/guides.py
gimkit/log.py
gimkit/models/__init__.py
gimkit/models/base.py
gimkit/models/openai.py
gimkit/models/utils.py
gimkit/models/vllm.py
gimkit/models/vllm_offline.py
gimkit/prompts.py
gimkit/py.typed
gimkit/schemas.py
gimkit-0.1.1.dist-info/WHEEL
gimkit-0.1.1.dist-info/METADATA
gimkit-0.1.1.dist-info/RECORD
