Metadata-Version: 2.3
Name: gimkit
Version: 0.1.1
Summary: Guided Infilling Modeling
Keywords: machine learning,deep learning,language models,structured generation,guided infilling
Author: Shichao Song
Author-email: Shichao Song <song.shichao@outlook.com>
License: MIT
Classifier: Development Status :: 5 - Production/Stable
Classifier: Intended Audience :: Developers
Classifier: Intended Audience :: Information Technology
Classifier: Intended Audience :: Science/Research
Classifier: Operating System :: OS Independent
Classifier: Programming Language :: Python :: 3
Classifier: Programming Language :: Python :: 3.10
Classifier: Programming Language :: Python :: 3.11
Classifier: Programming Language :: Python :: 3.12
Classifier: Programming Language :: Python :: 3.13
Classifier: Topic :: Scientific/Engineering :: Artificial Intelligence
Requires-Dist: json-repair>=0.55.1
Requires-Dist: llguidance>=1.3.0
Requires-Dist: outlines[openai]>=1.2.9
Requires-Dist: vllm>=0.14.0 ; extra == 'vllm'
Requires-Python: >=3.10
Project-URL: Documentation, https://github.com/SculptAI/GIMKit
Project-URL: Homepage, https://github.com/SculptAI/GIMKit
Project-URL: Issues, https://github.com/SculptAI/GIM/issues
Project-URL: Repository, https://github.com/SculptAI/GIMKit
Provides-Extra: vllm
